LICENSE
README.md
pyproject.toml
requirements.txt
phomemo/__init__.py
phomemo/print_p12.py
phomemo/render_label.py
phomemo_p12_tools.egg-info/PKG-INFO
phomemo_p12_tools.egg-info/SOURCES.txt
phomemo_p12_tools.egg-info/dependency_links.txt
phomemo_p12_tools.egg-info/entry_points.txt
phomemo_p12_tools.egg-info/requires.txt
phomemo_p12_tools.egg-info/top_level.txt
venv/bin/rst2html.py
venv/bin/rst2html4.py
venv/bin/rst2html5.py
venv/bin/rst2latex.py
venv/bin/rst2man.py
venv/bin/rst2odt.py
venv/bin/rst2odt_prepstyles.py
venv/bin/rst2pseudoxml.py
venv/bin/rst2s5.py
venv/bin/rst2xetex.py
venv/bin/rst2xml.py
venv/bin/rstpep2html.py