Metadata-Version: 2.1
Name: phomemo-p12-tools
Version: 0.0.5
Summary: Phomemo P12 printing tools
Author-email: TOKITA Hiroshi <tokita.hiroshi@gmail.com>
License: MIT License
Project-URL: homepage, https://github.com/soburi/phomemo-p12
Project-URL: repository, https://github.com/soburi/phomemo-p12
Classifier: Programming Language :: Python :: 3
Classifier: License :: OSI Approved :: MIT License
Classifier: Operating System :: OS Independent
Classifier: Topic :: System :: Hardware :: Hardware Drivers
License-File: LICENSE
